README.txt
setup.py
Products/__init__.py
Products.WorkflowField.egg-info/PKG-INFO
Products.WorkflowField.egg-info/SOURCES.txt
Products.WorkflowField.egg-info/dependency_links.txt
Products.WorkflowField.egg-info/entry_points.txt
Products.WorkflowField.egg-info/namespace_packages.txt
Products.WorkflowField.egg-info/not-zip-safe
Products.WorkflowField.egg-info/requires.txt
Products.WorkflowField.egg-info/top_level.txt
Products/WorkflowField/README.txt
Products/WorkflowField/__init__.py
Products/WorkflowField/_field.py
Products/WorkflowField/_widget.py
Products/WorkflowField/configure.zcml
Products/WorkflowField/version.txt
Products/WorkflowField/examples/__init__.py
Products/WorkflowField/examples/content.py
Products/WorkflowField/i18n/workflowfield-pt.po
Products/WorkflowField/i18n/workflowfield.pot
Products/WorkflowField/profiles/default/metadata.xml
Products/WorkflowField/profiles/default/skins.xml
Products/WorkflowField/profiles/example_types/metadata.xml
Products/WorkflowField/profiles/example_types/types.xml
Products/WorkflowField/profiles/example_types/types/ExampleWFFieldContent.xml
Products/WorkflowField/skins/workflowfield/workflow_widget.pt
Products/WorkflowField/tests/__init__.py
Products/WorkflowField/tests/test_content.py
docs/HISTORY.txt
docs/INSTALL.txt
docs/LICENSE.GPL
docs/LICENSE.txt