Metadata-Version: 1.0
Name: Products.WorkflowField
Version: 0.1b1
Summary: WorkflowField
Home-page: http://plone.org/products/workflowfield
Author: Jens Klein
Author-email: jens@bluedynamics.com
License: GPL
Keywords: plone workflow archetypes field
Platform: UNKNOWN
Classifier: Framework :: Plone
Classifier: Programming Language :: Python
Classifier: Topic :: Software Development :: Libraries :: Python Modules
